{
  "type": "forge:conditional",
  "recipes": [
    {
      "conditions": [
        {
          "type": "forge:mod_loaded",
          "modid": "occultism"
        }
      ],
      "recipe": {
        "type": "magichem:alchemical_composition",
        "distill_only": false,
        "output_rate": 1.0,
        "object": {
          "item": "occultism:otherstone"
        },
        "components": [
          {
            "item": "magichem:admixture_stone",
            "count": 3
          },
          {
            "item": "magichem:admixture_instrument",
            "count": 1
          },
          {
            "item": "magichem:admixture_spirit",
            "count": 1
          }
        ]
      }
    }
  ]
}